myinternshipcalculator2024/__init__.py
myinternshipcalculator2024/calculator.py
tests/__init__.py
tests/test_calculate_weekly_hours.py
tests/test_model.py
tests/test_plot.py
tests/test_stats.py
myinternshipcalculator2024-0.3.8.dist-info/LICENSE
myinternshipcalculator2024-0.3.8.dist-info/METADATA
myinternshipcalculator2024-0.3.8.dist-info/WHEEL
myinternshipcalculator2024-0.3.8.dist-info/top_level.txt
myinternshipcalculator2024-0.3.8.dist-info/RECORD
